fdt/__init__.py
fdt/__main__.py
fdt/header.py
fdt/items.py
fdt/misc.py
fdt-0.3.3.dist-info/LICENSE
fdt-0.3.3.dist-info/METADATA
fdt-0.3.3.dist-info/WHEEL
fdt-0.3.3.dist-info/entry_points.txt
fdt-0.3.3.dist-info/top_level.txt
fdt-0.3.3.dist-info/RECORD
